Metadata-Version: 2.1
Name: membernator
Version: 1.1.0
Summary: A tool that can be used to scan membership cards and
Home-page: https://gitlab.com/baldurmen/membernator
Author: Louis-Philippe Véronneau
License: ISC
Platform: UNKNOWN
Classifier: License :: OSI Approved :: ISC License (ISCL)
Classifier: Programming Language :: Python :: 3
Classifier: Programming Language :: Python :: 3.5
Classifier: Programming Language :: Python :: 3.6
Classifier: Programming Language :: Python :: 3.7
Classifier: Environment :: X11 Applications
Classifier: Intended Audience :: End Users/Desktop
Requires-Python: >=3.5.0
